sitemapper/__init__.py
sitemapper/__main__.py
sitemapper-1.1.2.data/data/LICENSE
sitemapper-1.1.2.data/data/VERSION
sitemapper-1.1.2.dist-info/DESCRIPTION.rst
sitemapper-1.1.2.dist-info/METADATA
sitemapper-1.1.2.dist-info/RECORD
sitemapper-1.1.2.dist-info/WHEEL
sitemapper-1.1.2.dist-info/entry_points.txt
sitemapper-1.1.2.dist-info/metadata.json
sitemapper-1.1.2.dist-info/top_level.txt
