Metadata-Version: 2.0
Name: sitemapper
Version: 1.1.2
Summary:   A tool for generating xml sitemaps from a list of urls.
Home-page: https://github.com/mmontagna/sitemapper
Author: Marco Montagna
Author-email: marcojoemontagna@gmail.com
License: Copyright (c) 2018 Marco Montagna
